Django_generate_serializers_views/__init__.py
Django_generate_serializers_views/apps.py
Django_generate_serializers_views/management/__init__.py
Django_generate_serializers_views/management/commands/__init__.py
Django_generate_serializers_views/management/commands/generate_serializers_views.py
Django_generate_serializers_views-0.2.1.dist-info/LICENSE
Django_generate_serializers_views-0.2.1.dist-info/METADATA
Django_generate_serializers_views-0.2.1.dist-info/WHEEL
Django_generate_serializers_views-0.2.1.dist-info/top_level.txt
Django_generate_serializers_views-0.2.1.dist-info/RECORD
