Metadata-Version: 2.1
Name: Django_generate_serializers_views
Version: 0.2.1
Summary: This package helps in generate the views.py and serializers.py with the auto-generated code.
Home-page: 
Author: ramesh patil
Author-email: rrp24999@gmail.com
Classifier: Programming Language :: Python :: 3
Classifier: License :: OSI Approved :: MIT License
Classifier: Operating System :: OS Independent
Requires-Python: >=3.6
License-File: LICENSE
